shap_explainer/__init__.py
shap_explainer/shap_explainer.py
shap_explainer-0.1.7.dist-info/METADATA
shap_explainer-0.1.7.dist-info/WHEEL
shap_explainer-0.1.7.dist-info/top_level.txt
shap_explainer-0.1.7.dist-info/RECORD
